task1/counter.sv
module counter #(
    parameter WIDTH = 8;
)(
    // interface signals
    input   logic               clk,    // clock
    input   logic               rst,    // reset
    input   logic               en,     // counter enable
    output  logic [WIDTH-1:0]   count   // count output
);

always_ff @ (posedge clk)
    if (rst)    count <= {WIDTH{1'b0}}; // non-blocking assignment, since we are in always_ff block
    else        count <= count + {{WIDTH-1{1'b0}}, en};
    
endmodule

task1/counter.vcd
$version Generated by VerilatedVcd $end
$timescale 1ps $end
 $scope module TOP $end
  $var wire 1 # clk $end
  $var wire 1 $ rst $end
  $var wire 1 % en $end
  $var wire 8 & count [7:0] $end
  $scope module counter $end
   $var wire 32 ' WIDTH [31:0] $end
   $var wire 1 # clk $end
   $var wire 1 $ rst $end
   $var wire 1 % en $end
   $var wire 8 & count [7:0] $end
  $upscope $end
 $upscope $end
$enddefinitions $end


#0
1#
1$
0%
b00000000 &
b00000000000000000000000000001000 '
#2
0#
1%
#4
b00000001 &
#6
0$
b00000010 &
#8
b00000011 &
#10
b00000100 &
#12
b00000101 &
#14
b00000110 &
#16
b00000111 &
#18
b00001000 &
#20
0%
b00001001 &
#22
#24
1%
#26
b00001010 &
#28
b00001011 &
#30
b00001100 &
#32
1$
b00000000 &
#34
0$
b00000001 &
#36
b00000010 &
#38
b00000011 &
#40
b00000100 &
#42
b00000101 &
#44
b00000110 &
#46
b00000111 &
#48
b00001000 &
#50
0%
b00001001 &
#52
#54
1%
#56
b00001010 &
#58
b00001011 &
#60
b00001100 &
#62
b00001101 &
#64
b00001110 &
#66
b00001111 &
#68
b00010000 &
#70
b00010001 &
#72
b00010010 &
#74
b00010011 &
#76
b00010100 &
#78
b00010101 &
#80
b00010110 &
#82
b00010111 &
#84
b00011000 &
#86
b00011001 &
#88
b00011010 &
#90
b00011011 &
#92
b00011100 &
#94
b00011101 &
#96
b00011110 &
#98
b00011111 &
#100
b00100000 &
#102
b00100001 &
#104
b00100010 &
#106
b00100011 &
#108
b00100100 &
#110
b00100101 &
#112
b00100110 &
#114
b00100111 &
#116
b00101000 &
#118
b00101001 &
#120
b00101010 &
#122
b00101011 &
#124
b00101100 &
#126
b00101101 &
#128
b00101110 &
#130
b00101111 &
#132
b00110000 &
#134
b00110001 &
#136
b00110010 &
#138
b00110011 &
#140
b00110100 &
#142
b00110101 &
#144
b00110110 &
#146
b00110111 &
#148
b00111000 &
#150
b00111001 &
#152
b00111010 &
#154
b00111011 &
#156
b00111100 &
#158
b00111101 &
#160
b00111110 &
#162
b00111111 &
#164
b01000000 &
#166
b01000001 &
#168
b01000010 &
#170
b01000011 &
#172
b01000100 &
#174
b01000101 &
#176
b01000110 &
#178
b01000111 &
#180
b01001000 &
#182
b01001001 &
#184
b01001010 &
#186
b01001011 &
#188
b01001100 &
#190
b01001101 &
#192
b01001110 &
#194
b01001111 &
#196
b01010000 &
#198
b01010001 &
#200
b01010010 &
#202
b01010011 &
#204
b01010100 &
#206
b01010101 &
#208
b01010110 &
#210
b01010111 &
#212
b01011000 &
#214
b01011001 &
#216
b01011010 &
#218
b01011011 &
#220
b01011100 &
#222
b01011101 &
#224
b01011110 &
#226
b01011111 &
#228
b01100000 &
#230
b01100001 &
#232
b01100010 &
#234
b01100011 &
#236
b01100100 &
#238
b01100101 &
#240
b01100110 &
#242
b01100111 &
#244
b01101000 &
#246
b01101001 &
#248
b01101010 &
#250
b01101011 &
#252
b01101100 &
#254
b01101101 &
#256
b01101110 &
#258
b01101111 &
#260
b01110000 &
#262
b01110001 &
#264
b01110010 &
#266
b01110011 &
#268
b01110100 &
#270
b01110101 &
#272
b01110110 &
#274
b01110111 &
#276
b01111000 &
#278
b01111001 &
#280
b01111010 &
#282
b01111011 &
#284
b01111100 &
#286
b01111101 &
#288
b01111110 &
#290
b01111111 &
#292
b10000000 &
#294
b10000001 &
#296
b10000010 &
#298
b10000011 &
#300
b10000100 &
#302
b10000101 &
#304
b10000110 &
#306
b10000111 &
#308
b10001000 &
#310
b10001001 &
#312
b10001010 &
#314
b10001011 &
#316
b10001100 &
#318
b10001101 &
#320
b10001110 &
#322
b10001111 &
#324
b10010000 &
#326
b10010001 &
#328
b10010010 &
#330
b10010011 &
#332
b10010100 &
#334
b10010101 &
#336
b10010110 &
#338
b10010111 &
#340
b10011000 &
#342
b10011001 &
#344
b10011010 &
#346
b10011011 &
#348
b10011100 &
#350
b10011101 &
#352
b10011110 &
#354
b10011111 &
#356
b10100000 &
#358
b10100001 &
#360
b10100010 &
#362
b10100011 &
#364
b10100100 &
#366
b10100101 &
#368
b10100110 &
#370
b10100111 &
#372
b10101000 &
#374
b10101001 &
#376
b10101010 &
#378
b10101011 &
#380
b10101100 &
#382
b10101101 &
#384
b10101110 &
#386
b10101111 &
#388
b10110000 &
#390
b10110001 &
#392
b10110010 &
#394
b10110011 &
#396
b10110100 &
#398
b10110101 &
#400
b10110110 &
#402
b10110111 &
#404
b10111000 &
#406
b10111001 &
#408
b10111010 &
#410
b10111011 &
#412
b10111100 &
#414
b10111101 &
#416
b10111110 &
#418
b10111111 &
#420
b11000000 &
#422
b11000001 &
#424
b11000010 &
#426
b11000011 &
#428
b11000100 &
#430
b11000101 &
#432
b11000110 &
#434
b11000111 &
#436
b11001000 &
#438
b11001001 &
#440
b11001010 &
#442
b11001011 &
#444
b11001100 &
#446
b11001101 &
#448
b11001110 &
#450
b11001111 &
#452
b11010000 &
#454
b11010001 &
#456
b11010010 &
#458
b11010011 &
#460
b11010100 &
#462
b11010101 &
#464
b11010110 &
#466
b11010111 &
#468
b11011000 &
#470
b11011001 &
#472
b11011010 &
#474
b11011011 &
#476
b11011100 &
#478
b11011101 &
#480
b11011110 &
#482
b11011111 &
#484
b11100000 &
#486
b11100001 &
#488
b11100010 &
#490
b11100011 &
#492
b11100100 &
#494
b11100101 &
#496
b11100110 &
#498
b11100111 &
#500
b11101000 &
#502
b11101001 &
#504
b11101010 &
#506
b11101011 &
#508
b11101100 &
#510
b11101101 &
#512
b11101110 &
#514
b11101111 &
#516
b11110000 &
#518
b11110001 &
#520
b11110010 &
#522
b11110011 &
#524
b11110100 &
#526
b11110101 &
#528
b11110110 &
#530
b11110111 &
#532
b11111000 &
#534
b11111001 &
#536
b11111010 &
#538
b11111011 &
#540
b11111100 &
#542
b11111101 &
#544
b11111110 &
#546
b11111111 &
#548
b00000000 &
#550
b00000001 &
#552
b00000010 &
#554
b00000011 &
#556
b00000100 &
#558
b00000101 &
#560
b00000110 &
#562
b00000111 &
#564
b00001000 &
#566
0%
b00001001 &
#568
#570
1%
#572
b00001010 &
#574
b00001011 &
#576
b00001100 &
#578
b00001101 &
#580
b00001110 &
#582
b00001111 &
#584
b00010000 &
#586
b00010001 &
#588
b00010010 &
#590
b00010011 &
#592
b00010100 &
#594
b00010101 &
#596
b00010110 &
#598
b00010111 &
